detapro/__init__.py
detapro/errors.py
detapro/userbase.py
detapro-0.1.0.dist-info/LICENSE
detapro-0.1.0.dist-info/WHEEL
detapro-0.1.0.dist-info/METADATA
detapro-0.1.0.dist-info/RECORD
